Xodia24/__init__.py
Xodia24/env.py
Xodia24/path.py
Xodia24-0.1.19.dist-info/LICENSE
Xodia24-0.1.19.dist-info/METADATA
Xodia24-0.1.19.dist-info/WHEEL
Xodia24-0.1.19.dist-info/top_level.txt
Xodia24-0.1.19.dist-info/RECORD
