Metadata-Version: 2.1
Name: Xodia24
Version: 0.1.19
Summary: Python package providing a custom environment for simulating tank battles
Author: Prem Gaikwad
Author-email: premgaikwad7a@gmail.com
Keywords: python,reinforcement-learning,tank-battle
Classifier: Development Status :: 1 - Planning
Classifier: Intended Audience :: Developers
Classifier: Programming Language :: Python :: 3
Classifier: Operating System :: Unix
Classifier: Operating System :: MacOS :: MacOS X
Classifier: Operating System :: Microsoft :: Windows
License-File: LICENSE
Requires-Dist: gymnasium
Requires-Dist: numpy
Requires-Dist: matplotlib
